prefix/etc/jupyter/jupyter_notebook_config.d/solara.json
prefix/etc/jupyter/jupyter_server_config.d/solara.json
solara/__init__.py
solara/__main__.py
solara/_stores.py
solara/alias.py
solara/autorouting.py
solara/cache.py
solara/checks.html
solara/checks.py
solara/comm.py
solara/core.py
solara/datatypes.py
solara/express.py
solara/kitchensink.py
solara/layout.py
solara/lifecycle.py
solara/minisettings.py
solara/py.typed
solara/reactive.py
solara/routing.py
solara/settings.py
solara/tasks.py
solara/toestand.py
solara/util.py
solara/validate_hooks.py
solara/components/__init__.py
solara/components/alert.py
solara/components/applayout.py
solara/components/button.py
solara/components/card.py
solara/components/checkbox.py
solara/components/code_highlight_css.py
solara/components/code_highlight_css.vue
solara/components/columns.py
solara/components/component_vue.py
solara/components/cross_filter.py
solara/components/dataframe.py
solara/components/datatable.py
solara/components/datatable.vue
solara/components/details.py
solara/components/download.vue
solara/components/echarts.py
solara/components/echarts.vue
solara/components/figure_altair.py
solara/components/file_browser.py
solara/components/file_download.py
solara/components/file_drop.py
solara/components/file_drop.vue
solara/components/file_list_widget.vue
solara/components/head.py
solara/components/head_tag.py
solara/components/head_tag.vue
solara/components/image.py
solara/components/input.py
solara/components/input_text_area.py
solara/components/link.py
solara/components/markdown.py
solara/components/markdown_editor.py
solara/components/markdown_editor.vue
solara/components/matplotlib.py
solara/components/meta.py
solara/components/misc.py
solara/components/pivot_table.py
solara/components/pivot_table.vue
solara/components/progress.py
solara/components/select.py
solara/components/select.vue
solara/components/slider.py
solara/components/slider_date.vue
solara/components/spinner-solara.vue
solara/components/spinner.py
solara_ui-1.57.1.dist-info/METADATA
solara_ui-1.57.1.dist-info/WHEEL
solara_ui-1.57.1.dist-info/licenses/LICENSE
solara_ui-1.57.1.dist-info/RECORD
