Metadata-Version: 2.3
Name: solara-ui
Version: 1.57.1
Dynamic: Summary
Project-URL: Home, https://www.github.com/widgetti/solara
Project-URL: Documentation, https://solara.dev
Author-email: "Maarten A. Breddels" <maartenbreddels@gmail.com>
License: The MIT License (MIT)
Classifier: License :: OSI Approved :: MIT License
Requires-Python: >=3.8
Requires-Dist: humanize
Requires-Dist: ipyvue>=1.9.0
Requires-Dist: ipyvuetify>=1.6.10
Requires-Dist: ipywidgets>=7.7
Requires-Dist: reacton>=1.9
Requires-Dist: requests
Provides-Extra: all
Requires-Dist: cachetools; extra == 'all'
Requires-Dist: markdown; extra == 'all'
Requires-Dist: numpy; extra == 'all'
Requires-Dist: pillow; extra == 'all'
Requires-Dist: pygments; extra == 'all'
Requires-Dist: pymdown-extensions; extra == 'all'
Provides-Extra: cache
Requires-Dist: cachetools; extra == 'cache'
Provides-Extra: extra
Requires-Dist: numpy; extra == 'extra'
Requires-Dist: pillow; extra == 'extra'
Provides-Extra: markdown
Requires-Dist: markdown; extra == 'markdown'
Requires-Dist: pygments; extra == 'markdown'
Requires-Dist: pymdown-extensions; extra == 'markdown'
